CHANGELOG.md
dt_apscanner.py
dt_apscanner-0.1.3.dist-info/entry_points.txt
dt_apscanner-0.1.3.dist-info/LICENSE
dt_apscanner-0.1.3.dist-info/METADATA
dt_apscanner-0.1.3.dist-info/WHEEL
dt_apscanner-0.1.3.dist-info/RECORD
