Metadata-Version: 2.1
Name: dt-apscanner
Version: 0.1.3
Summary: Wifi AP scanner tool
Author: JavaWiz
Author-email: JavaWiz1@hotmail.com
Requires-Python: >=3.10,<4.0
Classifier: Programming Language :: Python :: 3
Classifier: Programming Language :: Python :: 3.10
Classifier: Programming Language :: Python :: 3.11
Classifier: Programming Language :: Python :: 3.12
Requires-Dist: dt-net
Requires-Dist: loguru (>=0.7,<0.8)
